AUTHORS.rst
CONTRIBUTING.rst
HISTORY.rst
LICENSE
MANIFEST.in
README.rst
setup.py
pygazebo/__init__.py
pygazebo/pygazebo.py
pygazebo.egg-info/PKG-INFO
pygazebo.egg-info/SOURCES.txt
pygazebo.egg-info/dependency_links.txt
pygazebo.egg-info/not-zip-safe
pygazebo.egg-info/requires.txt
pygazebo.egg-info/top_level.txt
pygazebo/msg/__init__.py
pygazebo/msg/axis_pb2.py
pygazebo/msg/boxgeom_pb2.py
pygazebo/msg/camera_cmd_pb2.py
pygazebo/msg/camerasensor_pb2.py
pygazebo/msg/collision_pb2.py
pygazebo/msg/color_pb2.py
pygazebo/msg/contact_pb2.py
pygazebo/msg/contacts_pb2.py
pygazebo/msg/contactsensor_pb2.py
pygazebo/msg/cylindergeom_pb2.py
pygazebo/msg/diagnostics_pb2.py
pygazebo/msg/factory_pb2.py
pygazebo/msg/fog_pb2.py
pygazebo/msg/friction_pb2.py
pygazebo/msg/geometry_pb2.py
pygazebo/msg/gps_pb2.py
pygazebo/msg/gui_camera_pb2.py
pygazebo/msg/gui_overlay_config_pb2.py
pygazebo/msg/gui_pb2.py
pygazebo/msg/gz_string_pb2.py
pygazebo/msg/gz_string_v_pb2.py
pygazebo/msg/header_pb2.py
pygazebo/msg/heightmapgeom_pb2.py
pygazebo/msg/image_pb2.py
pygazebo/msg/image_stamped_pb2.py
pygazebo/msg/imagegeom_pb2.py
pygazebo/msg/images_stamped_pb2.py
pygazebo/msg/imu_pb2.py
pygazebo/msg/inertial_pb2.py
pygazebo/msg/int_pb2.py
pygazebo/msg/joint_animation_pb2.py
pygazebo/msg/joint_cmd_pb2.py
pygazebo/msg/joint_pb2.py
pygazebo/msg/joint_wrench_pb2.py
pygazebo/msg/joint_wrench_stamped_pb2.py
pygazebo/msg/laserscan_pb2.py
pygazebo/msg/laserscan_stamped_pb2.py
pygazebo/msg/light_pb2.py
pygazebo/msg/link_data_pb2.py
pygazebo/msg/link_pb2.py
pygazebo/msg/log_control_pb2.py
pygazebo/msg/log_status_pb2.py
pygazebo/msg/material_pb2.py
pygazebo/msg/meshgeom_pb2.py
pygazebo/msg/model_configuration_pb2.py
pygazebo/msg/model_pb2.py
pygazebo/msg/model_v_pb2.py
pygazebo/msg/packet_pb2.py
pygazebo/msg/physics_pb2.py
pygazebo/msg/pid_pb2.py
pygazebo/msg/planegeom_pb2.py
pygazebo/msg/plugin_pb2.py
pygazebo/msg/pointcloud_pb2.py
pygazebo/msg/pose_animation_pb2.py
pygazebo/msg/pose_pb2.py
pygazebo/msg/pose_stamped_pb2.py
pygazebo/msg/pose_trajectory_pb2.py
pygazebo/msg/pose_v_pb2.py
pygazebo/msg/poses_stamped_pb2.py
pygazebo/msg/projector_pb2.py
pygazebo/msg/propagation_grid_pb2.py
