Metadata-Version: 1.1
Name: pygazebo
Version: 3.0.0-2014.1
Summary: Python bindings for the Gazebo multi-robot simulator.
Home-page: https://github.com/jpieper/pygazebo
Author: Josh Pieper
Author-email: jjp@pobox.com
License: Apache License 2.0
Keywords: pygazebo
Platform: UNKNOWN
Classifier: Development Status :: 2 - Pre-Alpha
Classifier: Intended Audience :: Developers
Classifier: License :: OSI Approved :: Apache Software License
Classifier: Natural Language :: English
Classifier: Programming Language :: Python :: 2
Classifier: Programming Language :: Python :: 2.6
Classifier: Programming Language :: Python :: 2.7
Classifier: Topic :: Software Development :: Libraries :: Python Modules
Classifier: Topic :: Scientific/Engineering
